{"nodes": [{"id": "bbos_journey_roadmap", "label": "BBOS Journey: Four-Phase Roadmap", "file_type": "document", "source_file": ".graphify_website_staging/bbos/journey/index.md", "source_location": null, "source_url": null, "captured_at": null, "author": null, "contributor": null}, {"id": "bbos_journey_phase1_development", "label": "BBOS Phase 1: Development (Active, 88%)", "file_type": "document", "source_file": ".graphify_website_staging/bbos/journey/index.md", "source_location": null, "source_url": null, "captured_at": null, "author": null, "contributor": null}, {"id": "bbos_journey_phase2_validation", "label": "BBOS Phase 2: Validation", "file_type": "document", "source_file": ".graphify_website_staging/bbos/journey/index.md", "source_location": null, "source_url": null, "captured_at": null, "author": null, "contributor": null}, {"id": "bbos_journey_phase3_productization", "label": "BBOS Phase 3: Productization", "file_type": "document", "source_file": ".graphify_website_staging/bbos/journey/index.md", "source_location": null, "source_url": null, "captured_at": null, "author": null, "contributor": null}, {"id": "bbos_journey_phase4_distribution", "label": "BBOS Phase 4: Distribution", "file_type": "document", "source_file": ".graphify_website_staging/bbos/journey/index.md", "source_location": null, "source_url": null, "captured_at": null, "author": null, "contributor": null}, {"id": "nav_bbos_journey", "label": "BBOS Navigation: Journey Section", "file_type": "document", "source_file": ".graphify_website_staging/bbos/journey/index.md", "source_location": null, "source_url": null, "captured_at": null, "author": null, "contributor": null}], "edges": [{"source": "nav_bbos_journey", "target": "bbos_journey_roadmap", "relation": "implements", "confidence": "EXTRACTED", "confidence_score": 1.0, "source_file": ".graphify_website_staging/bbos/journey/index.md", "source_location": null, "weight": 1.0}, {"source": "bbos_journey_roadmap", "target": "bbos_journey_phase1_development", "relation": "implements", "confidence": "EXTRACTED", "confidence_score": 1.0, "source_file": ".graphify_website_staging/bbos/journey/index.md", "source_location": null, "weight": 1.0}, {"source": "bbos_journey_roadmap", "target": "bbos_journey_phase2_validation", "relation": "implements", "confidence": "EXTRACTED", "confidence_score": 1.0, "source_file": ".graphify_website_staging/bbos/journey/index.md", "source_location": null, "weight": 1.0}, {"source": "bbos_journey_roadmap", "target": "bbos_journey_phase3_productization", "relation": "implements", "confidence": "EXTRACTED", "confidence_score": 1.0, "source_file": ".graphify_website_staging/bbos/journey/index.md", "source_location": null, "weight": 1.0}, {"source": "bbos_journey_roadmap", "target": "bbos_journey_phase4_distribution", "relation": "implements", "confidence": "EXTRACTED", "confidence_score": 1.0, "source_file": ".graphify_website_staging/bbos/journey/index.md", "source_location": null, "weight": 1.0}, {"source": "bbos_journey_phase1_development", "target": "bbos_product_amanah_gate", "relation": "references", "confidence": "EXTRACTED", "confidence_score": 1.0, "source_file": ".graphify_website_staging/bbos/journey/index.md", "source_location": null, "weight": 1.0}, {"source": "bbos_journey_phase1_development", "target": "bbos_product_glabel_system", "relation": "references", "confidence": "EXTRACTED", "confidence_score": 1.0, "source_file": ".graphify_website_staging/bbos/journey/index.md", "source_location": null, "weight": 1.0}, {"source": "bbos_journey_phase1_development", "target": "bbos_product_no_ship_protocol", "relation": "references", "confidence": "EXTRACTED", "confidence_score": 1.0, "source_file": ".graphify_website_staging/bbos/journey/index.md", "source_location": null, "weight": 1.0}, {"source": "bbos_journey_phase3_productization", "target": "bbos_product_amanah_gate", "relation": "references", "confidence": "EXTRACTED", "confidence_score": 1.0, "source_file": ".graphify_website_staging/bbos/journey/index.md", "source_location": null, "weight": 1.0}, {"source": "bbos_journey_phase3_productization", "target": "bbos_product_glabel_system", "relation": "references", "confidence": "EXTRACTED", "confidence_score": 1.0, "source_file": ".graphify_website_staging/bbos/journey/index.md", "source_location": null, "weight": 1.0}], "hyperedges": []}